nonebot_plugin_code/__init__.py
nonebot_plugin_code/run.py
nonebot_plugin_code-0.0.8.dist-info/LICENSE
nonebot_plugin_code-0.0.8.dist-info/METADATA
nonebot_plugin_code-0.0.8.dist-info/WHEEL
nonebot_plugin_code-0.0.8.dist-info/top_level.txt
nonebot_plugin_code-0.0.8.dist-info/RECORD
