Metadata-Version: 2.1
Name: nonebot_plugin_code
Version: 0.0.8
Summary: nonebot2 plugin run code online
Home-page: https://github.com/yzyyz1387/nonebot_plugin_code
Author: yzyyz1387
Author-email: youzyyz1384@qq.com
Keywords: pip,nonebot2,nonebot,nonebot_plugin
Platform: any
Classifier: Programming Language :: Python :: 3
Classifier: License :: OSI Approved :: MIT License
Classifier: Operating System :: OS Independent
License-File: LICENSE
Requires-Dist: nonebot-adapter-onebot <3.0.0,>=2.0.0-beta.1
Requires-Dist: nonebot2 <3.0.0,>=2.0.0-beta.1
Requires-Dist: httpx >=0.19.0
